chainalysis/__init__.py
chainalysis/_constants.py
chainalysis/_data_solutions.py
chainalysis/_exceptions.py
chainalysis/_types.py
chainalysis/data_solutions.py
chainalysis/autotracing/_autotracing.py
chainalysis/orm/__init__.py
chainalysis/orm/_analytical_select.py
chainalysis/orm/_orm.py
chainalysis/orm/_select.py
chainalysis/orm/_transactional_select.py
chainalysis/sql/__init__.py
chainalysis/sql/_analytical.py
chainalysis/sql/_sql.py
chainalysis/sql/_transactional.py
chainalysis/util_functions/check_list_type.py
chainalysis/util_functions/requests.py
chainalysis/utils/__init__.py
chainalysis/utils/_stringify.py
chainalysis/utils/_utils.py
chainalysis-1.1.0.dist-info/METADATA
chainalysis-1.1.0.dist-info/WHEEL
chainalysis-1.1.0.dist-info/licenses/LICENCE
chainalysis-1.1.0.dist-info/RECORD
